{
  "name": "@steve/reddit-bot",
  "version": "0.0.6",
  "publish": true,
  "description": "",
  "env": [
    {
      "name": "AUTH_TOKEN",
      "defaultValue": "",
      "description": ""
    },
    {
      "name": "STDLIB_LIBRARY_TOKEN",
      "defaultValue": "",
      "description": ""
    },
    {
      "name": "REDDIT_SECRET",
      "defaultValue": "",
      "description": ""
    },
    {
      "name": "REDDIT_KEY",
      "defaultValue": "",
      "description": ""
    },
    {
      "name": "REDDIT_USERNAME",
      "defaultValue": "",
      "description": ""
    },
    {
      "name": "REDDIT_PASSWORD",
      "defaultValue": "",
      "description": ""
    }
  ]
}
